termill/__init__.py
termill-0.2.0.dist-info/WHEEL
termill-0.2.0.dist-info/METADATA
termill-0.2.0.dist-info/RECORD
