Metadata-Version: 2.1
Name: termill
Version: 0.2.0
Summary: 
Home-page: https://github.com/ikornaselur/termill
License: MIT
Author: Axel
Author-email: dev@absalon.is
Requires-Python: >=3.8,<4.0
Classifier: License :: OSI Approved :: MIT License
Classifier: Programming Language :: Python :: 3
Classifier: Programming Language :: Python :: 3.8
